{ "indexes" : [ { "v" : 1, "key" : { "_id" : 1 }, "name" : "_id_", "ns" : "workspace.workspaceObjVersions" }, { "v" : 1, "unique" : true, "key" : { "ws" : 1, "id" : 1, "ver" : 1 }, "name" : "ws_1_id_1_ver_1", "ns" : "workspace.workspaceObjVersions" }, { "v" : 1, "unique" : true, "key" : { "ws" : 1, "id" : 1, "ver" : -1 }, "name" : "ws_1_id_1_ver_-1", "ns" : "workspace.workspaceObjVersions" }, { "v" : 1, "key" : { "type" : 1, "chksum" : 1 }, "name" : "type_1_chksum_1", "ns" : "workspace.workspaceObjVersions" }, { "v" : 1, "key" : { "savedby" : 1 }, "name" : "savedby_1", "ns" : "workspace.workspaceObjVersions" }, { "v" : 1, "key" : { "refs" : 1 }, "name" : "refs_1", "ns" : "workspace.workspaceObjVersions", "sparse" : 1 }, { "v" : 1, "key" : { "provrefs" : 1 }, "name" : "provrefs_1", "ns" : "workspace.workspaceObjVersions", "sparse" : 1 }, { "v" : 1, "key" : { "provenance" : 1 }, "name" : "provenance_1", "ns" : "workspace.workspaceObjVersions" }, { "v" : 1, "key" : { "savedate" : 1 }, "name" : "savedate_1", "ns" : "workspace.workspaceObjVersions" }, { "v" : 1, "key" : { "meta" : 1 }, "name" : "meta_1", "ns" : "workspace.workspaceObjVersions", "sparse" : 1 } ] }